pyClusterWise/__init__.py
pyClusterWise/clustering.py
pyClusterWise-1.0.0.dist-info/LICENSE.txt
pyClusterWise-1.0.0.dist-info/METADATA
pyClusterWise-1.0.0.dist-info/WHEEL
pyClusterWise-1.0.0.dist-info/top_level.txt
pyClusterWise-1.0.0.dist-info/RECORD
