Metadata-Version: 2.1
Name: pyClusterWise
Version: 1.0.0
Summary: A Python package for dynamic clustering analysis with multiple methods and uncertainty evaluation.
Author: Behnam Sadeghi
Author-email: z5218858@zmail.unsw.edu.au
License: MIT
Classifier: Programming Language :: Python :: 3
Classifier: License :: OSI Approved :: MIT License
Classifier: Operating System :: OS Independent
Requires-Python: >=3.6
License-File: LICENSE.txt
Requires-Dist: pandas
Requires-Dist: numpy
Requires-Dist: matplotlib
Requires-Dist: scikit-learn
Requires-Dist: scipy
